bakbak.py
Bak_Bak-0.2.dist-info/LICENSE
Bak_Bak-0.2.dist-info/METADATA
Bak_Bak-0.2.dist-info/WHEEL
Bak_Bak-0.2.dist-info/top_level.txt
Bak_Bak-0.2.dist-info/RECORD
