Metadata-Version: 2.1
Name: Bak-Bak
Version: 0.2
Summary: A Python library for speech synthesis using SAPI.SpVoice
Classifier: Programming Language :: Python :: 3
Classifier: License :: OSI Approved :: MIT License
Classifier: Operating System :: OS Independent
Requires-Python: >=3.6
License-File: LICENSE
Requires-Dist: pypiwin32
